[
  {
    "time": "2025-07-24 11:05",
    "entry": 24489.7890625,
    "sl": 24193.80078125,
    "tp": 25081.765625,
    "type": "bullish"
  },
  {
    "time": "2025-07-24 11:45",
    "entry": 24437.580078125,
    "sl": 24424.66015625,
    "tp": 24463.419921875,
    "type": "bullish"
  },
  {
    "time": "2025-07-23 11:25",
    "entry": 24230.67,
    "sl": 24264.77,
    "tp": 24162.47,
    "type": "bearish"
  },
  {
    "time": "2025-07-23 12:00",
    "entry": 24217.1,
    "sl": 24254.88,
    "tp": 24141.54,
    "type": "bearish"
  },
  {
    "time": "2025-07-23 12:05",
    "entry": 24216.6,
    "sl": 24245.37,
    "tp": 24159.06,
    "type": "bearish"
  },
  {
    "time": "2025-07-23 12:50",
    "entry": 24187.93,
    "sl": 24213.42,
    "tp": 24136.95,
    "type": "bearish"
  },
  {
    "time": "2025-07-23 12:55",
    "entry": 24175.87,
    "sl": 24192.79,
    "tp": 24142.03,
    "type": "bearish"
  },
  {
    "time": "2025-07-23 13:00",
    "entry": 24165.62,
    "sl": 24179.87,
    "tp": 24137.12,
    "type": "bearish"
  },
  {
    "time": "2025-07-23 13:40",
    "entry": 24196.93,
    "sl": 24157.0,
    "tp": 24276.79,
    "type": "bullish"
  },
  {
    "time": "2025-07-23 14:25",
    "entry": 24198.52,
    "sl": 24185.57,
    "tp": 24224.42,
    "type": "bullish"
  },
  {
    "time": "2025-07-24 11:00",
    "entry": 24484.31,
    "sl": 24196.54,
    "tp": 25059.85,
    "type": "bullish"
  },
  {
    "time": "2025-07-24 11:15",
    "entry": 24464.1,
    "sl": 24482.84,
    "tp": 24426.62,
    "type": "bearish"
  },
  {
    "time": "2025-07-24 11:20",
    "entry": 24432.92,
    "sl": 24477.57,
    "tp": 24343.62,
    "type": "bearish"
  },
  {
    "time": "2025-07-24 11:25",
    "entry": 24438.1,
    "sl": 24461.59,
    "tp": 24391.12,
    "type": "bearish"
  },
  {
    "time": "2025-07-24 11:50",
    "entry": 24437.53,
    "sl": 24441.66,
    "tp": 24429.27,
    "type": "bearish"
  },
  {
    "time": "2025-07-24 12:00",
    "entry": 24392.17,
    "sl": 24427.68,
    "tp": 24321.15,
    "type": "bearish"
  },
  {
    "time": "2025-07-24 12:15",
    "entry": 24354.33,
    "sl": 24389.05,
    "tp": 24284.89,
    "type": "bearish"
  },
  {
    "time": "2025-07-24 12:20",
    "entry": 24348.31,
    "sl": 24368.86,
    "tp": 24307.21,
    "type": "bearish"
  },
  {
    "time": "2025-07-24 12:50",
    "entry": 24342.17,
    "sl": 24353.13,
    "tp": 24320.25,
    "type": "bearish"
  },
  {
    "time": "2025-07-24 12:55",
    "entry": 24337.01,
    "sl": 24342.77,
    "tp": 24325.49,
    "type": "bearish"
  },
  {
    "time": "2025-07-24 13:20",
    "entry": 24354.88,
    "sl": 24347.34,
    "tp": 24369.96,
    "type": "bullish"
  },
  {
    "time": "2025-07-24 13:40",
    "entry": 24379.83,
    "sl": 24364.6,
    "tp": 24410.29,
    "type": "bullish"
  },
  {
    "time": "2025-07-24 13:45",
    "entry": 24373.53,
    "sl": 24369.13,
    "tp": 24382.33,
    "type": "bullish"
  },
  {
    "time": "2025-07-24 13:55",
    "entry": 24352.48,
    "sl": 24373.06,
    "tp": 24311.32,
    "type": "bearish"
  },
  {
    "time": "2025-07-24 14:05",
    "entry": 24326.61,
    "sl": 24351.42,
    "tp": 24276.99,
    "type": "bearish"
  },
  {
    "time": "2025-07-24 14:10",
    "entry": 24338.6,
    "sl": 24342.12,
    "tp": 24331.56,
    "type": "bearish"
  },
  {
    "time": "2025-07-18 13:00",
    "entry": 24341.560546875,
    "sl": 24446.0703125,
    "tp": 24132.541015625,
    "type": "bearish"
  },
  {
    "time": "2025-07-18 14:00",
    "entry": 24343.3203125,
    "sl": 24358.689453125,
    "tp": 24312.58203125,
    "type": "bearish"
  },
  {
    "time": "2025-07-21 11:00",
    "entry": 24258.849609375,
    "sl": 24311.5,
    "tp": 24153.548828125,
    "type": "bearish"
  },
  {
    "time": "2025-07-21 12:00",
    "entry": 24228.8203125,
    "sl": 24279.349609375,
    "tp": 24127.76171875,
    "type": "bearish"
  },
  {
    "time": "2025-07-22 11:00",
    "entry": 24096.4296875,
    "sl": 24224.509765625,
    "tp": 23840.26953125,
    "type": "bearish"
  },
  {
    "time": "2025-07-22 12:00",
    "entry": 24058.2109375,
    "sl": 24217.640625,
    "tp": 23739.3515625,
    "type": "bearish"
  },
  {
    "time": "2025-07-23 11:00",
    "entry": 24247.91015625,
    "sl": 24082.859375,
    "tp": 24578.01171875,
    "type": "bullish"
  },
  {
    "time": "2025-07-23 12:00",
    "entry": 24175.869140625,
    "sl": 24067.5,
    "tp": 24392.607421875,
    "type": "bullish"
  },
  {
    "time": "2025-07-23 13:00",
    "entry": 24189.3203125,
    "sl": 24227.48046875,
    "tp": 24113.0,
    "type": "bearish"
  },
  {
    "time": "2025-07-24 11:00",
    "entry": 24401.259765625,
    "sl": 24205.0703125,
    "tp": 24793.638671875,
    "type": "bullish"
  },
  {
    "time": "2025-07-24 12:00",
    "entry": 24337.009765625,
    "sl": 24208.140625,
    "tp": 24594.748046875,
    "type": "bullish"
  },
  {
    "time": "2025-07-24 13:00",
    "entry": 24352.48046875,
    "sl": 24401.259765625,
    "tp": 24254.921875,
    "type": "bearish"
  }
]